LICENSE
ascii_generator/__init__.py
ascii_generator/computation/__init__.py
ascii_generator/computation/image_processing.py
ascii_generator/config/__init__.py
ascii_generator/config/constants.py
ascii_generator/integrations/__init__.py
ascii_generator/interface/__init__.py
ascii_generator/interface/command_line.py
ascii_generator/logs/__init__.py
ascii_generator/logs/setup_logging.py
ascii_generator/main.py
ascii_generator/py.typed
ascii_generator/utilities/__init__.py
ascii_generator/utilities/file_interaction.py
ascii_generator-1.2.0.dist-info/LICENSE
ascii_generator-1.2.0.dist-info/METADATA
ascii_generator-1.2.0.dist-info/WHEEL
ascii_generator-1.2.0.dist-info/entry_points.txt
ascii_generator-1.2.0.dist-info/RECORD
