Metadata-Version: 2.1
Name: ascii-generator
Version: 1.2.0
Summary: Converts a PNG file to ASCII art.
Home-page: https://github.com/unkokaeru/ascii-generator
License: MIT
Author: William Fayers
Author-email: wills@fayers.com
Requires-Python: >=3.10,<4.0
Classifier: License :: OSI Approved :: MIT License
Classifier: Programming Language :: Python :: 3
Classifier: Programming Language :: Python :: 3.10
Classifier: Programming Language :: Python :: 3.11
Classifier: Programming Language :: Python :: 3.12
Requires-Dist: numpy (>=2.1.1,<3.0.0)
Requires-Dist: pillow (>=10.4.0,<11.0.0)
Requires-Dist: rich (>=13.7.1,<14.0.0)
Project-URL: Repository, https://github.com/unkokaeru/ascii-generator
